{
  "properties":{
    "orgId":971365888684544,
    "orgName":"杨周测试项目部",
    "flowName":"测试的流程标题",
    "organization":"",
    "formName":"测试配置表单",
    "remark":"测试的",
    "systemMessage":false,
    "mailMessage":false,
    "noteMessage":false,
    "startRecall":false,
    "endRecall":false,
    "flowInitiator":false,
    "flowLog":true,
    "flowFormName":"测试配置表单",
    "flowFormId":1641505181685248,
    "productCode":"mq2",
    "moduleName":"",
    "flowState":"1",
    "moduleCode":"test"
  },
  "steps":[
    {
      "id":"b5fe374b-b28c-49e6-b59e-f9b2aee71ad3",
      "type":"start",
      "x":220,
      "y":220,
      "properties":{ }
    },
    {
      "id":"6d80f06c-711f-4eeb-814e-ac0e9b14d4f7",
      "type":"end",
      "x":1490,
      "y":220,
      "properties":{ }
    },
    {
      "id":"259ba0fd-bf38-49fb-831b-82fd893473a4",
      "type":"rect",
      "x":580,
      "y":220,
      "properties":{
        "text":"测试步骤1",
        "name":"",
        "user":"",
        "userId":0,
        "region":"",
        "type":"",
        "flowType":1,
        "carbonCopy":1,
        "opinion":"",
        "countersign":true,
        "step":"1",
        "sign":"1",
        "node":"",
        "buttons":[
          {
            "id":1127642163606529,
            "showTitle":"转交下一步",
            "sort":1
          },
          {
            "id":1127642163606536,
            "showTitle":"流程处理过程",
            "sort":7
          },
          {
            "id":1127642163606535,
            "showTitle":"阅知",
            "sort":3
          },
          {
            "id":1127642163606534,
            "showTitle":"完成",
            "sort":2
          },
          {
            "id":1127642163606532,
            "showTitle":"抄送",
            "sort":6
          },
          {
            "id":1127642163606531,
            "showTitle":"终止",
            "sort":5
          },
          {
            "id":1127642163606530,
            "showTitle":"驳回",
            "sort":4
          },
          {
            "id":1127642163606537,
            "showTitle":"打印",
            "sort":8
          }
        ],
        "stepType":"normal",
        "stepName":"测试步骤1",
        "dynamic":"预留",
        "dynamicField":"预留",
        "commentDisplay":true,
        "attachment":true,
        "signatureType":"",
        "handler":"",
        "handlePolicy":1,
        "handlePercentage":"",
        "CounterSignaturePolicy":"",
        "CounterSignaturePercentage":0,
        "backType":0,
        "backPolicy":0,
        "backStep":{
          "stepId":"",
          "stepName":""
        },
        "isCustomizeComment":false,
        "customizeComments":[ ],
        "stopRemark":"",
        "handType":0,
        "copyHandler":"",
        "copyUser":""
      },
      "text":{
        "x":580,
        "y":220,
        "value":"测试步骤1"
      }
    },
    {
      "id":"7f8538d4-9c6a-40a7-bafc-535e1e422ec9",
      "type":"rect",
      "x":770,
      "y":220,
      "properties":{
        "text":"步骤二",
        "name":"",
        "user":"",
        "userId":0,
        "region":"",
        "type":"",
        "flowType":1,
        "carbonCopy":1,
        "opinion":"",
        "countersign":true,
        "step":"1",
        "sign":"1",
        "node":"",
        "buttons":[ ],
        "stepType":"normal",
        "stepName":"步骤二",
        "dynamic":"预留",
        "dynamicField":"预留",
        "commentDisplay":true,
        "attachment":true,
        "signatureType":"",
        "handler":"",
        "handlePolicy":1,
        "handlePercentage":"",
        "CounterSignaturePolicy":"",
        "CounterSignaturePercentage":0,
        "backType":0,
        "backPolicy":0,
        "backStep":{
          "stepId":"",
          "stepName":""
        },
        "isCustomizeComment":false,
        "customizeComments":[ ],
        "stopRemark":"",
        "handType":0,
        "copyHandler":"",
        "copyUser":""
      },
      "text":{
        "x":770,
        "y":220,
        "value":"步骤二"
      }
    },
    {
      "id":"07cf28fc-939a-4d89-af95-7dae169cc4bb",
      "type":"rect",
      "x":1140,
      "y":220,
      "properties":{
        "text":"步骤三",
        "name":"",
        "user":"12345678900,###,AAA",
        "userId":0,
        "region":"",
        "type":"",
        "flowType":0,
        "carbonCopy":1,
        "opinion":"",
        "countersign":true,
        "step":"1",
        "sign":"1",
        "node":"",
        "buttons":[
          {
            "id":1127642163606535,
            "showTitle":"阅知",
            "sort":3
          },
          {
            "id":1127642163606534,
            "showTitle":"完成",
            "sort":2
          },
          {
            "id":1127642163606532,
            "showTitle":"抄送",
            "sort":6
          }
        ],
        "stepType":"normal",
        "stepName":"步骤三",
        "dynamic":"预留",
        "dynamicField":"预留",
        "commentDisplay":false,
        "attachment":true,
        "signatureType":"",
        "handler":"u_765962535539712,u_761023283016704,u_654300865499136",
        "handlePolicy":3,
        "handlePercentage":"",
        "CounterSignaturePolicy":"",
        "CounterSignaturePercentage":0,
        "backType":2,
        "backPolicy":2,
        "backStep":{
          "stepId":"",
          "stepName":""
        },
        "isCustomizeComment":true,
        "customizeComments":[
          "a=1",
          "b=3",
          "c=4"
        ],
        "stopRemark":"",
        "handType":"",
        "copyHandler":"u_760400575452160,u_654308416598016,u_760941541495808",
        "copyUser":"DDD,BBB,TTT"
      },
      "text":{
        "x":1140,
        "y":220,
        "value":"步骤三"
      }
    }
  ],
  "lines":[
    {
      "id":"68f7763e-99f9-4dbd-ae99-f5a0ebb51315",
      "type":"polyline",
      "sourceNodeId":"259ba0fd-bf38-49fb-831b-82fd893473a4",
      "targetNodeId":"7f8538d4-9c6a-40a7-bafc-535e1e422ec9",
      "startPoint":{
        "x":630,
        "y":220
      },
      "endPoint":{
        "x":720,
        "y":220
      },
      "properties":{
        "lineName":"步骤二之前的连线",
        "transferMode":3,
        "text":"",
        "context":"",
        "value":"",
        "sqlWhere":"a=1",
        "customizeValues":[ ]
      },
      "pointsList":[
        {
          "x":630,
          "y":220
        },
        {
          "x":720,
          "y":220
        }
      ]
    },
    {
      "id":"287ccb00-cae9-46d2-ab43-bbfc1990f849",
      "type":"polyline",
      "sourceNodeId":"b5fe374b-b28c-49e6-b59e-f9b2aee71ad3",
      "targetNodeId":"259ba0fd-bf38-49fb-831b-82fd893473a4",
      "startPoint":{
        "x":240,
        "y":220
      },
      "endPoint":{
        "x":530,
        "y":220
      },
      "properties":{
        "lineName":"start1111",
        "transferMode":2,
        "text":"",
        "context":"",
        "value":"",
        "sqlWhere":"",
        "customizeValues":[ ]
      },
      "pointsList":[
        {
          "x":240,
          "y":220
        },
        {
          "x":530,
          "y":220
        }
      ]
    },
    {
      "id":"596c7482-4ba6-40c7-a94d-b98c7a13dba1",
      "type":"polyline",
      "sourceNodeId":"07cf28fc-939a-4d89-af95-7dae169cc4bb",
      "targetNodeId":"6d80f06c-711f-4eeb-814e-ac0e9b14d4f7",
      "startPoint":{
        "x":1190,
        "y":220
      },
      "endPoint":{
        "x":1490,
        "y":240
      },
      "properties":{
        "lineName":"步骤三之后连线33333条件流转",
        "transferMode":3,
        "text":"",
        "context":"",
        "value":"",
        "sqlWhere":"a=1 and b=3",
        "customizeValues":[ ]
      },
      "pointsList":[
        {
          "x":1190,
          "y":220
        },
        {
          "x":1220,
          "y":220
        },
        {
          "x":1220,
          "y":270
        },
        {
          "x":1490,
          "y":270
        },
        {
          "x":1490,
          "y":240
        }
      ]
    },
    {
      "id":"989165fc-3129-492d-832d-502c18c38365",
      "type":"polyline",
      "sourceNodeId":"7f8538d4-9c6a-40a7-bafc-535e1e422ec9",
      "targetNodeId":"07cf28fc-939a-4d89-af95-7dae169cc4bb",
      "startPoint":{
        "x":820,
        "y":220
      },
      "endPoint":{
        "x":1090,
        "y":220
      },
      "properties":{
        "lineName":"步骤二22之后,自动流转",
        "transferMode":1,
        "text":"",
        "context":"",
        "value":"",
        "sqlWhere":"",
        "customizeValues":[ ]
      },
      "pointsList":[
        {
          "x":820,
          "y":220
        },
        {
          "x":1090,
          "y":220
        }
      ]
    },
    {
      "id":"1a4fcb36-0987-4195-962d-4762431b1e7e",
      "type":"polyline",
      "sourceNodeId":"b5fe374b-b28c-49e6-b59e-f9b2aee71ad3",
      "targetNodeId":"7f8538d4-9c6a-40a7-bafc-535e1e422ec9",
      "startPoint":{
        "x":240,
        "y":220
      },
      "endPoint":{
        "x":770,
        "y":260
      },
      "properties":{ },
      "pointsList":[
        {
          "x":240,
          "y":220
        },
        {
          "x":270,
          "y":220
        },
        {
          "x":270,
          "y":290
        },
        {
          "x":770,
          "y":290
        },
        {
          "x":770,
          "y":260
        }
      ]
    },
    {
      "id":"f1a53b70-7c0e-45ad-89c8-bd1f3e7fea01",
      "type":"polyline",
      "sourceNodeId":"b5fe374b-b28c-49e6-b59e-f9b2aee71ad3",
      "targetNodeId":"7f8538d4-9c6a-40a7-bafc-535e1e422ec9",
      "startPoint":{
        "x":220,
        "y":200
      },
      "endPoint":{
        "x":770,
        "y":180
      },
      "properties":{ },
      "pointsList":[
        {
          "x":220,
          "y":200
        },
        {
          "x":220,
          "y":150
        },
        {
          "x":770,
          "y":150
        },
        {
          "x":770,
          "y":180
        }
      ]
    }
  ]
}
